dataextractor
