Metadata-Version: 1.1
Name: dj-data-extractor
Version: 0.1.1
Summary: Utils for extracting data from dicts.
Home-page: https://github.com/kverdecia/dj-data-extractor
Author: Karel Antonio Verdecia Ortiz
Author-email: kverdecia@gmail.com
License: MIT
Keywords: dj-data-extractor
Platform: UNKNOWN
Classifier: Development Status :: 3 - Alpha
Classifier: Framework :: Django :: 1.11
Classifier: Framework :: Django :: 2.1
Classifier: Intended Audience :: Developers
Classifier: License :: OSI Approved :: BSD License
Classifier: Natural Language :: English
Classifier: Programming Language :: Python :: 2
Classifier: Programming Language :: Python :: 2.7
Classifier: Programming Language :: Python :: 3
Classifier: Programming Language :: Python :: 3.5
Classifier: Programming Language :: Python :: 3.6
